handyneo/__init__.py
handyneo/handyneo.py
handyneo/inrun_test.py
handyneo/utils.py
handyneo-0.0.11.dist-info/LICENSE
handyneo-0.0.11.dist-info/METADATA
handyneo-0.0.11.dist-info/WHEEL
handyneo-0.0.11.dist-info/top_level.txt
handyneo-0.0.11.dist-info/RECORD
