Metadata-Version: 2.1
Name: handyneo
Version: 0.0.11
Summary: Facade for neo4j to create nodes and relationships in a more robust way
Author: ProxPxD (Piotr Maliszewski)
Keywords: handy,handyneo,neo,neo4j
License-File: LICENSE
